interpret_text/__init__.py
interpret_text/experimental/__init__.py
interpret_text/experimental/classical.py
interpret_text/experimental/explanation.py
interpret_text/experimental/unified_information.py
interpret_text/experimental/common/__init__.py
interpret_text/experimental/common/base_explainer.py
interpret_text/experimental/common/base_text_model.py
interpret_text/experimental/common/base_text_tokenizer.py
interpret_text/experimental/common/constants.py
interpret_text/experimental/common/structured_model_mixin.py
interpret_text/experimental/common/text_explainer_utils.py
interpret_text/experimental/common/timer.py
interpret_text/experimental/common/utils_bert.py
interpret_text/experimental/common/utils_classical.py
interpret_text/experimental/common/utils_introspective_rationale.py
interpret_text/experimental/common/utils_pytorch.py
interpret_text/experimental/common/utils_unified.py
interpret_text/experimental/common/model_config/__init__.py
interpret_text/experimental/common/model_config/base_model_config.py
interpret_text/experimental/common/model_config/introspective_rationale_model_config.py
interpret_text/experimental/common/model_config/model_config_constants.py
interpret_text/experimental/common/preprocessor/__init__.py
interpret_text/experimental/common/preprocessor/base_text_preprocessor.py
interpret_text/experimental/common/preprocessor/bert_preprocessor.py
interpret_text/experimental/common/preprocessor/glove_preprocessor.py
interpret_text/experimental/introspective_rationale/__init__.py
interpret_text/experimental/introspective_rationale/components.py
interpret_text/experimental/introspective_rationale/explainer.py
interpret_text/experimental/introspective_rationale/model.py
interpret_text/experimental/widget/ExplanationDashboard.py
interpret_text/experimental/widget/ExplanationWidget.py
interpret_text/experimental/widget/__init__.py
interpret_text/experimental/widget/_version.py
interpret_text/experimental/widget/_internal/__init__.py
anilv_interpret_text-0.0.1.dist-info/LICENSE
anilv_interpret_text-0.0.1.dist-info/METADATA
anilv_interpret_text-0.0.1.dist-info/WHEEL
anilv_interpret_text-0.0.1.dist-info/top_level.txt
anilv_interpret_text-0.0.1.dist-info/RECORD
