Metadata-Version: 2.1
Name: anilv-interpret-text
Version: 0.0.1
Summary: Generates pickle for Encoder
Home-page: https://o365exchange.visualstudio.com/O365%20Sandbox/_git/IPMLExp?path=%2Fsrc%2FPanini2%2FSyntheticDataGenerator&version=GBmaster
Author: Anil Vemula
Author-email: v-anvemu@microsoft.com
License: UNKNOWN
Platform: UNKNOWN
Classifier: Programming Language :: Python :: 3
Classifier: License :: OSI Approved :: MIT License
Classifier: Operating System :: OS Independent
Requires-Python: >=3.6
Requires-Dist: numpy
Requires-Dist: pandas
Requires-Dist: pydantic
Requires-Dist: spacy
Requires-Dist: ipywidgets
Requires-Dist: transformers (==2.4.1)
Requires-Dist: scipy
Requires-Dist: scikit-learn
Requires-Dist: tqdm
Requires-Dist: cached-property
Requires-Dist: interpret-community
Requires-Dist: shap (<=0.29.3,>=0.20.0)
